{"card_name": "Spirit of Flight", "color": "U", "rarity": "common", "type": "Enchantment Creature \u2013 Bird Spirit", "number": 71, "color_identity": "U", "cost": "{1}{U}", "rules_text": "Flying\nUnearth {1}{U} [i]({1}{U}: Return this card from your graveyard to the battlefield. It gains haste. Exile it at the beginning of the end step or if it would leave the battlefield. Unearth only as a sorcery.)[/i]", "pt": "2/1", "special_text": "", "shape": "normal", "set": "MHQ", "loyalty": "", "notes": ""}