{"card_name": "Escape from Thuul's Clutches", "color": "G", "rarity": "uncommon", "type": "Artifact \u2013 Manuscript", "number": 146, "color_identity": "G", "cost": "{1}{G}", "rules_text": "", "pt": "", "special_text": "[i](Choose only one page as a sorcery to add its effects.)[/i]\nWhen [i]Escape from Thuul\u2019s Clutches[/i] enters the battlefield, create a 2/2 green Beast creature token.\n{G} Page 11\n{T}: Put a +1/+1 counter on target creature you control. Activate only as a sorcery.\n{G} Page 21\n{G}, {T}, Sacrifice [i]Escape from Thuul\u2019s Clutches[/i]: Target creature you control fights target creature you don\u2019t control. Activate only as a sorcery.", "shape": "class", "set": "CYO", "loyalty": "", "notes": ""}