{"card_name": "Edict of Mortality", "color": "R", "rarity": "rare", "type": "Sorcery", "number": 126, "color_identity": "R", "cost": "{1}{R}", "rules_text": "Edict of Mortality deal 3 damage to any target. If this spell was engraved, Edict of Mortality deals 7 damage instead.\nEngrave 3\u2013{3}{R}{R} [i](If you cast this spell for {3}{R}{R}, create a 0/0 Sculpture artifact creature token, then distribute three +1/+1 counters among Sculptures you control.)[/i]", "pt": "", "special_text": "", "shape": "normal", "set": "AKI", "loyalty": "", "notes": ""}