{"card_name": "Temple to Ghazuz", "color": "RG", "rarity": "mythic", "type": "Enchantment", "number": 230, "color_identity": "RG", "cost": "{R}{G}", "rules_text": "{RG}, Sacrifice a creature: Add {R}{G} and put a blood counter on Temple to Ghazuz.\nAs long as Temple to Ghazuz has three or more blood counters on it, it\u2019s a land with \u201c{T}: Add {R}{G}.\u201d [i](It\u2019s no longer an enchantment.)[/i]", "pt": "", "special_text": "", "shape": "normal", "set": "AKI", "loyalty": "", "notes": "", "image_type": "png"}