{"card_name": "Lingering Victim", "color": "R", "rarity": "uncommon", "type": "Creature \u2013 Spirit", "number": 154, "color_identity": "R", "cost": "{1}{R}{R}", "rules_text": "Regression {3}{R} [i](If you cast this for its regression cost, it has haste. Sacrifice it at the beginning of your next upkeep and create a 1/1 copy of it with haste.)[/i]\nWhenever a creature dies, add {R}. Until end of turn, you don\u2019t lose this mana as steps and phases end.", "pt": "3/2", "special_text": "", "shape": "normal", "set": "FBI", "loyalty": "", "notes": "", "image_type": "png"}