{"card_name": "Refuse to Repent", "color": "WR", "rarity": "rare", "type": "Sorcery", "number": 231, "color_identity": "WR", "cost": "{1}{R}{W}", "rules_text": "Penance {1}{R}{W} [i](If you cast this for its penance cost, replace all numbers in brackets with the greatest power or toughness among your creatures.)[/i]\nThis spell has lifelink if you cast it for its penance cost.\nRefuse to Repent deals [3] damage to each creature, planeswalker, and battle.", "pt": "", "special_text": "", "shape": "normal", "set": "666", "loyalty": "", "notes": "", "image_type": "png"}