{"card_name": "Fungal Growth", "color": "G", "rarity": "common", "type": "Sorcery", "number": 175, "color_identity": "G", "cost": "{1}{G}", "rules_text": "You may put a land card from your hand onto the battlefield tapped.\nImplant {1}{G} [i](As you cast a creature spell, you may reveal this card from your hand and pay its implant cost. If you do, that spell gains \u201cWhen this creature enters the battlefield\u201d and this card\u2019s effects.)[/i]", "pt": "", "special_text": "", "shape": "normal", "set": "XSK", "loyalty": "", "notes": "", "image_type": "png"}