{"card_name": "Specimen Alpha", "color": "UR", "rarity": "rare", "type": "Legendary Creature \u2013 Octopus Demon", "number": 225, "color_identity": "UR", "cost": "{1}{U}{R}", "rules_text": "{2}{U}{R}: Diverge 3/12 or 9/3{ }{ }{(}{I}{f}{ }{t}{h}{i}{s}{ }{c}{r}{e}{a}{t}{u}{r}{e}{ }{i}{s}{n}{\u2019}{t}{ }{a}{ }{M}{u}{t}{a}{n}{t}{,}{ }{i}{t}{s}{ }{b}{a}{s}{e}{ }{p}{o}{w}{e}{r}{ }{a}{n}{d}{ }{t}{o}{u}{g}{h}{n}{e}{s}{s}{ }{b}{e}{c}{o}{m}{e}{ }{y}{o}{u}{r}{ }{c}{h}{o}{i}{c}{e}{ }{o}{f}{ }{31}{2}{ }{o}{r}{ }9/3 and it becomes a Mutant in addition to its other types. Diverge only as a sorcery.)\nWhen Specimen Alpha diverges, discard your hand and draw three cards.", "pt": "3/3", "special_text": "", "shape": "normal", "set": "XSK", "loyalty": "", "notes": ""}