{"card_name": "Riftspawn Mosher", "color": "G", "rarity": "common", "type": "Creature \u2013 Beast", "number": 138, "color_identity": "G", "cost": "{4}{G}", "rules_text": "Vigilance, trample", "flavor_text": "[i]As the realms sundered during the Schism, some creatures were trapped in the Space Between the Notes, warping in horrifying, freestyle-fusion ways.[/i]", "pt": "5/4", "special_text": "", "shape": "normal", "set": "HVY", "loyalty": "", "artist": "Victor Maristane", "notes": "", "image_type": "png"}