{"card_name": "Idol of the Church of Shred", "color": "WU", "rarity": "common", "type": "Artifact Creature \u2013 Golem", "number": 234, "color_identity": "WU", "cost": "{1}", "rules_text": "{2}, {T}: Add {W}{W}, {W}{U}, or {U}{U}.\n{3}{W}{WU}{U}: Put three +1/+1 counters on Idol of the Church of Shred. It gains flying. Activate only as a sorcery and only once.", "flavor_text": "[i][/i]", "pt": "1/1", "special_text": "", "shape": "normal", "set": "HVY", "loyalty": "", "artist": "Miro Petrov", "notes": "", "image_type": "jpg"}