[
    {
        "card_name": "Hidden Heretic",
        "number": 1,
        "shape": "normal",
        "set": "ARK",
        "position": ""
    },
    {
        "card_name": "e"
    },
    {
        "card_name": "e"
    },
    {
        "card_name": "e"
    },
    {
        "card_name": "e"
    },
    {
        "card_name": "er"
    },
    {
        "card_name": "er"
    },
    {
        "card_name": "er"
    },
    {
        "card_name": "er"
    },
    {
        "card_name": "er"
    },
    {
        "card_name": "Speak No Evil",
        "number": 30,
        "shape": "normal",
        "set": "ARK",
        "position": ""
    },
    {
        "card_name": "Forbidden Ritual",
        "number": 46,
        "shape": "normal",
        "set": "ARK",
        "position": ""
    },
    {
        "card_name": "Pilgrimage of Sin",
        "number": 90,
        "shape": "normal",
        "set": "ARK",
        "position": ""
    },
    {
        "card_name": "Fall from Grace",
        "number": 106,
        "shape": "normal",
        "set": "ARK",
        "position": ""
    },
    {
        "card_name": "Crawling Canopy",
        "number": 142,
        "shape": "normal",
        "set": "ARK",
        "position": ""
    },
    {
        "card_name": "Crisis of Faith",
        "number": 5,
        "shape": "normal",
        "set": "ARK",
        "position": ""
    },
    {
        "card_name": "Alchemical Lore",
        "number": 35,
        "shape": "normal",
        "set": "ARK",
        "position": ""
    },
    {
        "card_name": "Carrion Gorger",
        "number": 72,
        "shape": "normal",
        "set": "ARK",
        "position": ""
    },
    {
        "card_name": "Barsil, Learned Heretic",
        "number": 101,
        "shape": "normal",
        "set": "ARK",
        "position": ""
    },
    {
        "card_name": "Beyond the North Winds",
        "number": 134,
        "shape": "normal",
        "set": "ARK",
        "position": ""
    },
    {
        "card_name": "Gensis, Witchfinder General",
        "number": 7,
        "shape": "normal",
        "set": "ARK",
        "position": ""
    },
    {
        "card_name": "Cryptic Grotesque",
        "number": 39,
        "shape": "normal",
        "set": "ARK",
        "position": ""
    },
    {
        "card_name": "Cilebios, Arch-Cantor",
        "number": 73,
        "shape": "normal",
        "set": "ARK",
        "position": ""
    },
    {
        "card_name": "Catechismal Lore",
        "number": 103,
        "shape": "normal",
        "set": "ARK",
        "position": ""
    },
    {
        "card_name": "Cino of the Gallow's Fen",
        "number": 140,
        "shape": "normal",
        "set": "ARK",
        "position": ""
    },
    {
        "card_name": "Heretical Lore",
        "number": 11,
        "shape": "normal",
        "set": "ARK",
        "position": ""
    },
    {
        "card_name": "Divinity through Blood",
        "number": 42,
        "shape": "normal",
        "set": "ARK",
        "position": ""
    },
    {
        "card_name": "Collector of Curiosities",
        "number": 74,
        "shape": "normal",
        "set": "ARK",
        "position": ""
    },
    {
        "card_name": "Cult Uprising",
        "number": 104,
        "shape": "normal",
        "set": "ARK",
        "position": ""
    },
    {
        "card_name": "Comical Lore",
        "number": 141,
        "shape": "normal",
        "set": "ARK",
        "position": ""
    },
    {
        "card_name": "Keeper of Liturgy",
        "number": 16,
        "shape": "normal",
        "set": "ARK",
        "position": ""
    },
    {
        "card_name": "Harvest Effigy",
        "number": 49,
        "shape": "normal",
        "set": "ARK",
        "position": ""
    },
    {
        "card_name": "Death Cult",
        "number": 77,
        "shape": "normal",
        "set": "ARK",
        "position": ""
    },
    {
        "card_name": "Divinity through Fire",
        "number": 105,
        "shape": "normal",
        "set": "ARK",
        "position": ""
    },
    {
        "card_name": "Cult Apprentice",
        "number": 143,
        "shape": "normal",
        "set": "ARK",
        "position": ""
    },
    {
        "card_name": "Myth of Akhillos",
        "number": 19,
        "shape": "normal",
        "set": "ARK",
        "position": ""
    },
    {
        "card_name": "The Holy Fools",
        "number": 50,
        "shape": "normal",
        "set": "ARK",
        "position": ""
    },
    {
        "card_name": "Diabolic Intent",
        "number": 78,
        "shape": "normal",
        "set": "ARK",
        "position": ""
    },
    {
        "card_name": "Midnight Rite",
        "number": 117,
        "shape": "normal",
        "set": "ARK",
        "position": ""
    },
    {
        "card_name": "Erythrogoyf",
        "number": 146,
        "shape": "normal",
        "set": "ARK",
        "position": ""
    },
    {
        "card_name": "Profane Penitent",
        "number": 23,
        "shape": "normal",
        "set": "ARK",
        "position": ""
    },
    {
        "card_name": "Legacy of Mutation",
        "number": 53,
        "shape": "normal",
        "set": "ARK",
        "position": ""
    },
    {
        "card_name": "Primal Lore",
        "number": 91,
        "shape": "normal",
        "set": "ARK",
        "position": ""
    },
    {
        "card_name": "Scion of Akhillos",
        "number": 128,
        "shape": "normal",
        "set": "ARK",
        "position": ""
    },
    {
        "card_name": "Unspeakable Progeny",
        "number": 161,
        "shape": "normal",
        "set": "ARK",
        "position": ""
    },
    {
        "card_name": "Prowling Childcatcher",
        "number": 24,
        "shape": "normal",
        "set": "ARK",
        "position": ""
    },
    {
        "card_name": "Stolen Apocrypha",
        "number": 62,
        "shape": "normal",
        "set": "ARK",
        "position": ""
    },
    {
        "card_name": "Weepwood Sovereign",
        "number": 97,
        "shape": "normal",
        "set": "ARK",
        "position": ""
    },
    {
        "card_name": "Suffer Not the Witch",
        "number": 130,
        "shape": "normal",
        "set": "ARK",
        "position": ""
    },
    {
        "card_name": "Weepwood Flow",
        "number": 163,
        "shape": "normal",
        "set": "ARK",
        "position": ""
    },
    {
        "card_name": "Ardent Blacksmith",
        "number": 2,
        "shape": "normal",
        "set": "ARK",
        "position": ""
    },
    {
        "card_name": "Cacophonous Fool",
        "number": 37,
        "shape": "normal",
        "set": "ARK",
        "position": ""
    },
    {
        "card_name": "Blasted Desolation",
        "number": 70,
        "shape": "normal",
        "set": "ARK",
        "position": ""
    },
    {
        "card_name": "Firebrand Orator",
        "number": 108,
        "shape": "normal",
        "set": "ARK",
        "position": ""
    },
    {
        "card_name": "Bleating Blasphemy",
        "number": 135,
        "shape": "normal",
        "set": "ARK",
        "position": ""
    },
    {
        "card_name": "Cleave to Faith",
        "number": 4,
        "shape": "normal",
        "set": "ARK",
        "position": ""
    },
    {
        "card_name": "Eldritch Engraving",
        "number": 43,
        "shape": "normal",
        "set": "ARK",
        "position": ""
    },
    {
        "card_name": "Corrupting Smog",
        "number": 76,
        "shape": "normal",
        "set": "ARK",
        "position": ""
    },
    {
        "card_name": "Into the Coven",
        "number": 113,
        "shape": "normal",
        "set": "ARK",
        "position": ""
    },
    {
        "card_name": "Carnival Procession",
        "number": 138,
        "shape": "normal",
        "set": "ARK",
        "position": ""
    },
    {
        "card_name": "Harsh Inquistior",
        "number": 10,
        "shape": "normal",
        "set": "ARK",
        "position": ""
    },
    {
        "card_name": "Fooling Around",
        "number": 45,
        "shape": "normal",
        "set": "ARK",
        "position": ""
    },
    {
        "card_name": "Eldritch Moon",
        "number": 79,
        "shape": "normal",
        "set": "ARK",
        "position": ""
    },
    {
        "card_name": "Lonely Fisherman",
        "number": 114,
        "shape": "normal",
        "set": "ARK",
        "position": ""
    },
    {
        "card_name": "Dour Fisherman",
        "number": 145,
        "shape": "normal",
        "set": "ARK",
        "position": ""
    },
    {
        "card_name": "Inquisitor's Carriage",
        "number": 13,
        "shape": "normal",
        "set": "ARK",
        "position": ""
    },
    {
        "card_name": "Frantic Musician",
        "number": 47,
        "shape": "normal",
        "set": "ARK",
        "position": ""
    },
    {
        "card_name": "False Pontiff",
        "number": 81,
        "shape": "normal",
        "set": "ARK",
        "position": ""
    },
    {
        "card_name": "Merciless Purge",
        "number": 116,
        "shape": "normal",
        "set": "ARK",
        "position": ""
    },
    {
        "card_name": "Fervent Blacksmith",
        "number": 147,
        "shape": "normal",
        "set": "ARK",
        "position": ""
    },
    {
        "card_name": "Keen-Eyed Merchant",
        "number": 15,
        "shape": "normal",
        "set": "ARK",
        "position": ""
    },
    {
        "card_name": "Mask of Geesh",
        "number": 54,
        "shape": "normal",
        "set": "ARK",
        "position": ""
    },
    {
        "card_name": "Gregarious Butcher",
        "number": 84,
        "shape": "normal",
        "set": "ARK",
        "position": ""
    },
    {
        "card_name": "Mystic Invocation",
        "number": 118,
        "shape": "normal",
        "set": "ARK",
        "position": ""
    },
    {
        "card_name": "Grinning Ringleader",
        "number": 150,
        "shape": "normal",
        "set": "ARK",
        "position": ""
    },
    {
        "card_name": "Living Saint",
        "number": 17,
        "shape": "normal",
        "set": "ARK",
        "position": ""
    },
    {
        "card_name": "Midnight Screecher",
        "number": 56,
        "shape": "normal",
        "set": "ARK",
        "position": ""
    },
    {
        "card_name": "The Horror Beyond",
        "number": 85,
        "shape": "normal",
        "set": "ARK",
        "position": ""
    },
    {
        "card_name": "Ominous Butcher",
        "number": 119,
        "shape": "normal",
        "set": "ARK",
        "position": ""
    },
    {
        "card_name": "Heretic's Amulet",
        "number": 152,
        "shape": "normal",
        "set": "ARK",
        "position": ""
    },
    {
        "card_name": "Novice Witchfinder",
        "number": 21,
        "shape": "normal",
        "set": "ARK",
        "position": ""
    },
    {
        "card_name": "Rousing Innkeeper",
        "number": 57,
        "shape": "normal",
        "set": "ARK",
        "position": ""
    },
    {
        "card_name": "Isolated Woodsman",
        "number": 86,
        "shape": "normal",
        "set": "ARK",
        "position": ""
    },
    {
        "card_name": "Persecuted Penitant",
        "number": 123,
        "shape": "normal",
        "set": "ARK",
        "position": ""
    },
    {
        "card_name": "Lord of Savages",
        "number": 154,
        "shape": "normal",
        "set": "ARK",
        "position": ""
    },
    {
        "card_name": "Offering to Divinity",
        "number": 22,
        "shape": "normal",
        "set": "ARK",
        "position": ""
    },
    {
        "card_name": "Serene Speculation",
        "number": 58,
        "shape": "normal",
        "set": "ARK",
        "position": ""
    },
    {
        "card_name": "Moon-Blotter Nightwing",
        "number": 88,
        "shape": "normal",
        "set": "ARK",
        "position": ""
    },
    {
        "card_name": "Praise the Shifting Flame",
        "number": 124,
        "shape": "normal",
        "set": "ARK",
        "position": ""
    },
    {
        "card_name": "Mischievous Masque",
        "number": 156,
        "shape": "normal",
        "set": "ARK",
        "position": ""
    },
    {
        "card_name": "Righteous Zeal",
        "number": 27,
        "shape": "normal",
        "set": "ARK",
        "position": ""
    },
    {
        "card_name": "Sharp-Tongued Merchant",
        "number": 59,
        "shape": "normal",
        "set": "ARK",
        "position": ""
    },
    {
        "card_name": "Shadow of the Crypt",
        "number": 92,
        "shape": "normal",
        "set": "ARK",
        "position": ""
    },
    {
        "card_name": "Ritualist of Vo'Radh",
        "number": 125,
        "shape": "normal",
        "set": "ARK",
        "position": ""
    },
    {
        "card_name": "Roar of Strength",
        "number": 157,
        "shape": "normal",
        "set": "ARK",
        "position": ""
    },
    {
        "card_name": "Veneration of Relics",
        "number": 31,
        "shape": "normal",
        "set": "ARK",
        "position": ""
    },
    {
        "card_name": "Shibboleth Amulet",
        "number": 60,
        "shape": "normal",
        "set": "ARK",
        "position": ""
    },
    {
        "card_name": "Strict Innkeeper",
        "number": 93,
        "shape": "normal",
        "set": "ARK",
        "position": ""
    },
    {
        "card_name": "Scholar of Secrets",
        "number": 127,
        "shape": "normal",
        "set": "ARK",
        "position": ""
    },
    {
        "card_name": "Sail into Despair",
        "number": 158,
        "shape": "normal",
        "set": "ARK",
        "position": ""
    },
    {
        "card_name": "Weeping Martyr",
        "number": 33,
        "shape": "normal",
        "set": "ARK",
        "position": ""
    },
    {
        "card_name": "Trickster of Geesh",
        "number": 64,
        "shape": "normal",
        "set": "ARK",
        "position": ""
    },
    {
        "card_name": "Sullen Synod",
        "number": 94,
        "shape": "normal",
        "set": "ARK",
        "position": ""
    },
    {
        "card_name": "Scourge the Soul",
        "number": 129,
        "shape": "normal",
        "set": "ARK",
        "position": ""
    },
    {
        "card_name": "Sift through the Bones",
        "number": 159,
        "shape": "normal",
        "set": "ARK",
        "position": ""
    },
    {
        "card_name": "Worm-Tongue Pontiff",
        "number": 34,
        "shape": "normal",
        "set": "ARK",
        "position": ""
    },
    {
        "card_name": "Witch's Sabbath",
        "number": 67,
        "shape": "normal",
        "set": "ARK",
        "position": ""
    },
    {
        "card_name": "Yog's Scorn",
        "number": 100,
        "shape": "normal",
        "set": "ARK",
        "position": ""
    },
    {
        "card_name": "Witchfinder's Scorn",
        "number": 132,
        "shape": "normal",
        "set": "ARK",
        "position": ""
    },
    {
        "card_name": "Tincture Peddler",
        "number": 160,
        "shape": "normal",
        "set": "ARK",
        "position": ""
    },
    {
        "card_name": "Backwater Farmhand",
        "number": 3,
        "shape": "normal",
        "set": "ARK",
        "position": ""
    },
    {
        "card_name": "Brooding Coven",
        "number": 36,
        "shape": "normal",
        "set": "ARK",
        "position": ""
    },
    {
        "card_name": "Architect of Fear",
        "number": 68,
        "shape": "normal",
        "set": "ARK",
        "position": ""
    },
    {
        "card_name": "Bolt of Vo'Radh",
        "number": 102,
        "shape": "normal",
        "set": "ARK",
        "position": ""
    },
    {
        "card_name": "Blessing of Change",
        "number": 136,
        "shape": "normal",
        "set": "ARK",
        "position": ""
    },
    {
        "card_name": "Faithwing Apprentice",
        "number": 6,
        "shape": "normal",
        "set": "ARK",
        "position": ""
    },
    {
        "card_name": "Covetous Whispers",
        "number": 38,
        "shape": "normal",
        "set": "ARK",
        "position": ""
    },
    {
        "card_name": "Blasphemous Howl",
        "number": 69,
        "shape": "normal",
        "set": "ARK",
        "position": ""
    },
    {
        "card_name": "Fireband Inquisitor",
        "number": 107,
        "shape": "normal",
        "set": "ARK",
        "position": ""
    },
    {
        "card_name": "Braying Outcast",
        "number": 137,
        "shape": "normal",
        "set": "ARK",
        "position": ""
    },
    {
        "card_name": "Gevangis Nightwatch",
        "number": 8,
        "shape": "normal",
        "set": "ARK",
        "position": ""
    },
    {
        "card_name": "Curious Specimen",
        "number": 40,
        "shape": "normal",
        "set": "ARK",
        "position": ""
    },
    {
        "card_name": "By the Light of the Moon",
        "number": 71,
        "shape": "normal",
        "set": "ARK",
        "position": ""
    },
    {
        "card_name": "Forged in Faith",
        "number": 109,
        "shape": "normal",
        "set": "ARK",
        "position": ""
    },
    {
        "card_name": "Carrion Gnawer",
        "number": 139,
        "shape": "normal",
        "set": "ARK",
        "position": ""
    },
    {
        "card_name": "Hallowed Raptor",
        "number": 9,
        "shape": "normal",
        "set": "ARK",
        "position": ""
    },
    {
        "card_name": "Disciple of Vo'Radh",
        "number": 41,
        "shape": "normal",
        "set": "ARK",
        "position": ""
    },
    {
        "card_name": "Consult the Sigils",
        "number": 75,
        "shape": "normal",
        "set": "ARK",
        "position": ""
    },
    {
        "card_name": "Gathering of Witches",
        "number": 110,
        "shape": "normal",
        "set": "ARK",
        "position": ""
    },
    {
        "card_name": "The Danse Macabre",
        "number": 144,
        "shape": "normal",
        "set": "ARK",
        "position": ""
    },
    {
        "card_name": "Holy Feast",
        "number": 12,
        "shape": "normal",
        "set": "ARK",
        "position": ""
    },
    {
        "card_name": "Ethereal Chains",
        "number": 44,
        "shape": "normal",
        "set": "ARK",
        "position": ""
    },
    {
        "card_name": "Evangel of Corvash",
        "number": 80,
        "shape": "normal",
        "set": "ARK",
        "position": ""
    },
    {
        "card_name": "Gnarled Acolyte",
        "number": 111,
        "shape": "normal",
        "set": "ARK",
        "position": ""
    },
    {
        "card_name": "Gift of Corvash",
        "number": 148,
        "shape": "normal",
        "set": "ARK",
        "position": ""
    },
    {
        "card_name": "Itinerant Cultist",
        "number": 14,
        "shape": "normal",
        "set": "ARK",
        "position": ""
    },
    {
        "card_name": "Frantic Scrawl",
        "number": 48,
        "shape": "normal",
        "set": "ARK",
        "position": ""
    },
    {
        "card_name": "Far from Pious Eyes",
        "number": 82,
        "shape": "normal",
        "set": "ARK",
        "position": ""
    },
    {
        "card_name": "Hearth Crawler",
        "number": 112,
        "shape": "normal",
        "set": "ARK",
        "position": ""
    },
    {
        "card_name": "Gnarled Wretch",
        "number": 149,
        "shape": "normal",
        "set": "ARK",
        "position": ""
    },
    {
        "card_name": "Martyr's Hymn",
        "number": 18,
        "shape": "normal",
        "set": "ARK",
        "position": ""
    },
    {
        "card_name": "Killing Joke",
        "number": 51,
        "shape": "normal",
        "set": "ARK",
        "position": ""
    },
    {
        "card_name": "The Fear in the Woods",
        "number": 83,
        "shape": "normal",
        "set": "ARK",
        "position": ""
    },
    {
        "card_name": "March of the Flagellants",
        "number": 115,
        "shape": "normal",
        "set": "ARK",
        "position": ""
    },
    {
        "card_name": "Heretic Harlequin",
        "number": 151,
        "shape": "normal",
        "set": "ARK",
        "position": ""
    },
    {
        "card_name": "Nightwing Hunter",
        "number": 20,
        "shape": "normal",
        "set": "ARK",
        "position": ""
    },
    {
        "card_name": "Leering Jester",
        "number": 52,
        "shape": "normal",
        "set": "ARK",
        "position": ""
    },
    {
        "card_name": "Knee Deep in the Dead",
        "number": 87,
        "shape": "normal",
        "set": "ARK",
        "position": ""
    },
    {
        "card_name": "Ominous Sorcerer",
        "number": 120,
        "shape": "normal",
        "set": "ARK",
        "position": ""
    },
    {
        "card_name": "Icon of Sin",
        "number": 153,
        "shape": "normal",
        "set": "ARK",
        "position": ""
    },
    {
        "card_name": "Purge Superstition",
        "number": 25,
        "shape": "normal",
        "set": "ARK",
        "position": ""
    },
    {
        "card_name": "Midnight Haunter",
        "number": 55,
        "shape": "normal",
        "set": "ARK",
        "position": ""
    },
    {
        "card_name": "Morgue Prowler",
        "number": 89,
        "shape": "normal",
        "set": "ARK",
        "position": ""
    },
    {
        "card_name": "Outrider of the Eagle",
        "number": 121,
        "shape": "normal",
        "set": "ARK",
        "position": ""
    },
    {
        "card_name": "Might of the Weepwood",
        "number": 155,
        "shape": "normal",
        "set": "ARK",
        "position": ""
    },
    {
        "card_name": "Rats in the Walls",
        "number": 26,
        "shape": "normal",
        "set": "ARK",
        "position": ""
    },
    {
        "card_name": "Sinister Summoner",
        "number": 61,
        "shape": "normal",
        "set": "ARK",
        "position": ""
    },
    {
        "card_name": "Thy Flesh Consumed",
        "number": 95,
        "shape": "normal",
        "set": "ARK",
        "position": ""
    },
    {
        "card_name": "Paranoid Fear",
        "number": 122,
        "shape": "normal",
        "set": "ARK",
        "position": ""
    },
    {
        "card_name": "Vaulting Acrobat",
        "number": 162,
        "shape": "normal",
        "set": "ARK",
        "position": ""
    },
    {
        "card_name": "Sainted Eagle",
        "number": 28,
        "shape": "normal",
        "set": "ARK",
        "position": ""
    },
    {
        "card_name": "Thirst for Mirth",
        "number": 63,
        "shape": "normal",
        "set": "ARK",
        "position": ""
    },
    {
        "card_name": "Weepwood Offering",
        "number": 96,
        "shape": "normal",
        "set": "ARK",
        "position": ""
    },
    {
        "card_name": "Sacred Censer",
        "number": 126,
        "shape": "normal",
        "set": "ARK",
        "position": ""
    },
    {
        "card_name": "Weepwood's Clutches",
        "number": 164,
        "shape": "normal",
        "set": "ARK",
        "position": ""
    },
    {
        "card_name": "Solemn Deacon",
        "number": 29,
        "shape": "normal",
        "set": "ARK",
        "position": ""
    },
    {
        "card_name": "What Happens in Secret",
        "number": 65,
        "shape": "normal",
        "set": "ARK",
        "position": ""
    },
    {
        "card_name": "Withered Oracle",
        "number": 98,
        "shape": "normal",
        "set": "ARK",
        "position": ""
    },
    {
        "card_name": "Weepwood Hunger",
        "number": 131,
        "shape": "normal",
        "set": "ARK",
        "position": ""
    },
    {
        "card_name": "Whispered Warning",
        "number": 165,
        "shape": "normal",
        "set": "ARK",
        "position": ""
    },
    {
        "card_name": "Votive Offering",
        "number": 32,
        "shape": "normal",
        "set": "ARK",
        "position": ""
    },
    {
        "card_name": "Witching Hour",
        "number": 66,
        "shape": "normal",
        "set": "ARK",
        "position": ""
    },
    {
        "card_name": "Yog's Flagellant",
        "number": 99,
        "shape": "normal",
        "set": "ARK",
        "position": ""
    },
    {
        "card_name": "Zealous Witchfinder",
        "number": 133,
        "shape": "normal",
        "set": "ARK",
        "position": ""
    },
    {
        "card_name": "Wretched Mendicant",
        "number": 166,
        "shape": "normal",
        "set": "ARK",
        "position": ""
    },
    {
        "card_name": "er"
    },
    {
        "card_name": "er"
    },
    {
        "card_name": "er"
    },
    {
        "card_name": "er"
    },
    {
        "card_name": "er"
    },
    {
        "card_name": "Procession of Souls",
        "number": 173,
        "shape": "normal",
        "set": "ARK",
        "position": ""
    },
    {
        "card_name": "The Black Goat of Weepwood",
        "number": 192,
        "shape": "normal",
        "set": "ARK",
        "position": ""
    },
    {
        "card_name": "Carnival of Chaos",
        "number": 217,
        "shape": "normal",
        "set": "ARK",
        "position": ""
    },
    {
        "card_name": "Kristana, the Blood Gyre",
        "number": 184,
        "shape": "normal",
        "set": "ARK",
        "position": ""
    },
    {
        "card_name": "Cardinal Sin",
        "number": 204,
        "shape": "normal",
        "set": "ARK",
        "position": ""
    },
    {
        "card_name": "Saint Goustun the Fair",
        "number": 174,
        "shape": "normal",
        "set": "ARK",
        "position": ""
    },
    {
        "card_name": "Lord of the Woods",
        "number": 196,
        "shape": "normal",
        "set": "ARK",
        "position": ""
    },
    {
        "card_name": "Delowe, Jester of Geesh",
        "number": 221,
        "shape": "normal",
        "set": "ARK",
        "position": ""
    },
    {
        "card_name": "Wrack the Mind",
        "number": 190,
        "shape": "normal",
        "set": "ARK",
        "position": ""
    },
    {
        "card_name": "Theonomarch Zofiya Cek",
        "number": 214,
        "shape": "normal",
        "set": "ARK",
        "position": ""
    },
    {
        "card_name": "Confluence of Yog",
        "number": 168,
        "shape": "normal",
        "set": "ARK",
        "position": ""
    },
    {
        "card_name": "Confluence of Corvash",
        "number": 193,
        "shape": "normal",
        "set": "ARK",
        "position": ""
    },
    {
        "card_name": "Change and Be Merry",
        "number": 218,
        "shape": "normal",
        "set": "ARK",
        "position": ""
    },
    {
        "card_name": "Confluence of Vo'Radh",
        "number": 180,
        "shape": "normal",
        "set": "ARK",
        "position": ""
    },
    {
        "card_name": "The Coming of the Eagle",
        "number": 205,
        "shape": "normal",
        "set": "ARK",
        "position": ""
    },
    {
        "card_name": "Savage Sacrament",
        "number": 175,
        "shape": "normal",
        "set": "ARK",
        "position": ""
    },
    {
        "card_name": "Shrine of Inner Shadows",
        "number": 199,
        "shape": "normal",
        "set": "ARK",
        "position": ""
    },
    {
        "card_name": "Confluence of Geesh",
        "number": 219,
        "shape": "normal",
        "set": "ARK",
        "position": ""
    },
    {
        "card_name": "Shrine of Shifting Flame",
        "number": 186,
        "shape": "normal",
        "set": "ARK",
        "position": ""
    },
    {
        "card_name": "Confluence of Akhillos",
        "number": 206,
        "shape": "normal",
        "set": "ARK",
        "position": ""
    },
    {
        "card_name": "Shrine of Hushed Prayer",
        "number": 177,
        "shape": "normal",
        "set": "ARK",
        "position": ""
    },
    {
        "card_name": "Teachings of Corvash",
        "number": 200,
        "shape": "normal",
        "set": "ARK",
        "position": ""
    },
    {
        "card_name": "Shrine of Boundless Mirth",
        "number": 225,
        "shape": "normal",
        "set": "ARK",
        "position": ""
    },
    {
        "card_name": "Summoned Shapestealer",
        "number": 188,
        "shape": "normal",
        "set": "ARK",
        "position": ""
    },
    {
        "card_name": "Shrine of Martyred Blood",
        "number": 213,
        "shape": "normal",
        "set": "ARK",
        "position": ""
    },
    {
        "card_name": "Hallowdark Borderpost",
        "number": 171,
        "shape": "normal",
        "set": "ARK",
        "position": ""
    },
    {
        "card_name": "Avram Von, Hellseeker",
        "number": 191,
        "shape": "normal",
        "set": "ARK",
        "position": ""
    },
    {
        "card_name": "Ghiacci, the Great Joker",
        "number": 222,
        "shape": "normal",
        "set": "ARK",
        "position": ""
    },
    {
        "card_name": "Gore Omen",
        "number": 183,
        "shape": "normal",
        "set": "ARK",
        "position": ""
    },
    {
        "card_name": "Fiercehallow Borderpost",
        "number": 208,
        "shape": "normal",
        "set": "ARK",
        "position": ""
    },
    {
        "card_name": "Iskanter, Blighted Bishop",
        "number": 172,
        "shape": "normal",
        "set": "ARK",
        "position": ""
    },
    {
        "card_name": "Darkrot Borderpost",
        "number": 194,
        "shape": "normal",
        "set": "ARK",
        "position": ""
    },
    {
        "card_name": "Rotwater Borderpost",
        "number": 224,
        "shape": "normal",
        "set": "ARK",
        "position": ""
    },
    {
        "card_name": "The Stolen Shape",
        "number": 187,
        "shape": "normal",
        "set": "ARK",
        "position": ""
    },
    {
        "card_name": "Hand of the Eagle",
        "number": 210,
        "shape": "normal",
        "set": "ARK",
        "position": ""
    },
    {
        "card_name": "Solemn Heresiarch",
        "number": 178,
        "shape": "normal",
        "set": "ARK",
        "position": ""
    },
    {
        "card_name": "Lurking Witch",
        "number": 197,
        "shape": "normal",
        "set": "ARK",
        "position": ""
    },
    {
        "card_name": "Soul of Wit",
        "number": 226,
        "shape": "normal",
        "set": "ARK",
        "position": ""
    },
    {
        "card_name": "Waterfierce Borderpost",
        "number": 189,
        "shape": "normal",
        "set": "ARK",
        "position": ""
    },
    {
        "card_name": "Metropolite Dmitry XII",
        "number": 212,
        "shape": "normal",
        "set": "ARK",
        "position": ""
    },
    {
        "card_name": "Folk Ritual",
        "number": 170,
        "shape": "normal",
        "set": "ARK",
        "position": ""
    },
    {
        "card_name": "Forbidden Goliath",
        "number": 195,
        "shape": "normal",
        "set": "ARK",
        "position": ""
    },
    {
        "card_name": "Blessing of Geesh",
        "number": 215,
        "shape": "normal",
        "set": "ARK",
        "position": ""
    },
    {
        "card_name": "Disciple of Blood",
        "number": 181,
        "shape": "normal",
        "set": "ARK",
        "position": ""
    },
    {
        "card_name": "Blood and Thunder",
        "number": 203,
        "shape": "normal",
        "set": "ARK",
        "position": ""
    },
    {
        "card_name": "Shambling Sanctuary",
        "number": 176,
        "shape": "normal",
        "set": "ARK",
        "position": ""
    },
    {
        "card_name": "Ritual of the Woods",
        "number": 198,
        "shape": "normal",
        "set": "ARK",
        "position": ""
    },
    {
        "card_name": "Mischievous Troupe",
        "number": 223,
        "shape": "normal",
        "set": "ARK",
        "position": ""
    },
    {
        "card_name": "Obsessive Alchemist",
        "number": 185,
        "shape": "normal",
        "set": "ARK",
        "position": ""
    },
    {
        "card_name": "Impulsive Inquisitor",
        "number": 211,
        "shape": "normal",
        "set": "ARK",
        "position": ""
    },
    {
        "card_name": "er"
    },
    {
        "card_name": "er"
    },
    {
        "card_name": "er"
    },
    {
        "card_name": "er"
    },
    {
        "card_name": "er"
    },
    {
        "card_name": "Creation Myth",
        "number": 227,
        "shape": "normal",
        "set": "ARK",
        "position": ""
    },
    {
        "card_name": "e"
    },
    {
        "card_name": "e"
    },
    {
        "card_name": "e"
    },
    {
        "card_name": "e"
    },
    {
        "card_name": "er"
    },
    {
        "card_name": "er"
    },
    {
        "card_name": "er"
    },
    {
        "card_name": "er"
    },
    "a->twobrid",
    {
        "card_name": "Coven's Offering",
        "number": 169,
        "shape": "normal",
        "set": "ARK",
        "position": ""
    },
    {
        "card_name": "Twisted Fealty",
        "number": 201,
        "shape": "normal",
        "set": "ARK",
        "position": ""
    },
    {
        "card_name": "Cacophony of Flesh",
        "number": 216,
        "shape": "normal",
        "set": "ARK",
        "position": ""
    },
    {
        "card_name": "Flense the Mind",
        "number": 182,
        "shape": "normal",
        "set": "ARK",
        "position": ""
    },
    {
        "card_name": "Fiery Penance",
        "number": 209,
        "shape": "normal",
        "set": "ARK",
        "position": ""
    },
    {
        "card_name": "Callous Chaplain",
        "number": 167,
        "shape": "normal",
        "set": "ARK",
        "position": ""
    },
    {
        "card_name": "Weepwood Null",
        "number": 202,
        "shape": "normal",
        "set": "ARK",
        "position": ""
    },
    {
        "card_name": "Costumed Cultist",
        "number": 220,
        "shape": "normal",
        "set": "ARK",
        "position": ""
    },
    {
        "card_name": "Captive Beastman",
        "number": 179,
        "shape": "normal",
        "set": "ARK",
        "position": ""
    },
    {
        "card_name": "Devout Harrier",
        "number": 207,
        "shape": "normal",
        "set": "ARK",
        "position": ""
    },
    {
        "card_name": "er"
    },
    {
        "card_name": "er"
    },
    {
        "card_name": "er"
    },
    {
        "card_name": "er"
    },
    "a->hybrid",
    {
        "card_name": "Acolyte of All Things",
        "number": 228,
        "shape": "normal",
        "set": "ARK",
        "position": ""
    },
    {
        "card_name": "Brutal Coven",
        "number": 232,
        "shape": "normal",
        "set": "ARK",
        "position": ""
    },
    {
        "card_name": "Laughter of Geesh",
        "number": 237,
        "shape": "normal",
        "set": "ARK",
        "position": ""
    },
    {
        "card_name": "Cloistered Cultist",
        "number": 230,
        "shape": "normal",
        "set": "ARK",
        "position": ""
    },
    {
        "card_name": "Procession of Faith",
        "number": 235,
        "shape": "normal",
        "set": "ARK",
        "position": ""
    },
    {
        "card_name": "Initiate of Balance",
        "number": 229,
        "shape": "normal",
        "set": "ARK",
        "position": ""
    },
    {
        "card_name": "Initiate of Strength",
        "number": 233,
        "shape": "normal",
        "set": "ARK",
        "position": ""
    },
    {
        "card_name": "Initiate of Change",
        "number": 236,
        "shape": "normal",
        "set": "ARK",
        "position": ""
    },
    {
        "card_name": "Initiate of Fire",
        "number": 231,
        "shape": "normal",
        "set": "ARK",
        "position": ""
    },
    {
        "card_name": "Initiate of the Eagle",
        "number": 234,
        "shape": "normal",
        "set": "ARK",
        "position": ""
    },
    {
        "card_name": "er"
    },
    {
        "card_name": "er"
    },
    {
        "card_name": "er"
    },
    {
        "card_name": "er"
    },
    "a->colorless",
    {
        "card_name": "Crypt of the Eagle",
        "number": 239,
        "shape": "normal",
        "set": "ARK",
        "position": ""
    },
    {
        "card_name": "Folk Altar",
        "number": 241,
        "shape": "normal",
        "set": "ARK",
        "position": ""
    },
    {
        "card_name": "Shield of Church and State",
        "number": 246,
        "shape": "normal",
        "set": "ARK",
        "position": ""
    },
    {
        "card_name": "Heretical Grimoire",
        "number": 242,
        "shape": "normal",
        "set": "ARK",
        "position": ""
    },
    {
        "card_name": "Ominous Idol",
        "number": 244,
        "shape": "normal",
        "set": "ARK",
        "position": ""
    },
    {
        "card_name": "Anointed Reliquary",
        "number": 238,
        "shape": "normal",
        "set": "ARK",
        "position": ""
    },
    {
        "card_name": "Cultic Relic",
        "number": 240,
        "shape": "normal",
        "set": "ARK",
        "position": ""
    },
    {
        "card_name": "Leering Crowcatcher",
        "number": 243,
        "shape": "normal",
        "set": "ARK",
        "position": ""
    },
    {
        "card_name": "Rag and Bone Cart",
        "number": 245,
        "shape": "normal",
        "set": "ARK",
        "position": ""
    },
    {
        "card_name": "Shriekhorn",
        "number": 247,
        "shape": "normal",
        "set": "ARK",
        "position": ""
    },
    {
        "card_name": "er"
    },
    {
        "card_name": "er"
    },
    {
        "card_name": "er"
    },
    {
        "card_name": "er"
    },
    {
        "card_name": "er"
    },
    {
        "card_name": "Crypt of Lies",
        "number": 251,
        "shape": "normal",
        "set": "ARK",
        "position": ""
    },
    {
        "card_name": "Crypt of Potential",
        "number": 253,
        "shape": "normal",
        "set": "ARK",
        "position": ""
    },
    {
        "card_name": "Crypt of Filth",
        "number": 249,
        "shape": "normal",
        "set": "ARK",
        "position": ""
    },
    {
        "card_name": "Crypt of Penance",
        "number": 252,
        "shape": "normal",
        "set": "ARK",
        "position": ""
    },
    {
        "card_name": "Crypt of Growth",
        "number": 250,
        "shape": "normal",
        "set": "ARK",
        "position": ""
    },
    {
        "card_name": "Occult Chamber",
        "number": 261,
        "shape": "normal",
        "set": "ARK",
        "position": ""
    },
    {
        "card_name": "Forbidden Library",
        "number": 255,
        "shape": "normal",
        "set": "ARK",
        "position": ""
    },
    {
        "card_name": "Gnarled Backwoods",
        "number": 257,
        "shape": "normal",
        "set": "ARK",
        "position": ""
    },
    {
        "card_name": "Imposing Basilica",
        "number": 259,
        "shape": "normal",
        "set": "ARK",
        "position": ""
    },
    {
        "card_name": "Land's End",
        "number": 260,
        "shape": "normal",
        "set": "ARK",
        "position": ""
    },
    {
        "card_name": "er"
    },
    {
        "card_name": "er"
    },
    {
        "card_name": "er"
    },
    {
        "card_name": "er"
    },
    {
        "card_name": "er"
    },
    {
        "card_name": "Hole in the World",
        "number": 258,
        "shape": "normal",
        "set": "ARK",
        "position": ""
    },
    {
        "card_name": "Faithbound Cloister",
        "number": 254,
        "shape": "normal",
        "set": "ARK",
        "position": ""
    },
    {
        "card_name": "Forsaken Chapel",
        "number": 256,
        "shape": "normal",
        "set": "ARK",
        "position": ""
    },
    {
        "card_name": "Congregant's Cathedral",
        "number": 248,
        "shape": "normal",
        "set": "ARK",
        "position": ""
    },
    {
        "card_name": "e"
    },
    {
        "card_name": "er"
    },
    {
        "card_name": "er"
    },
    {
        "card_name": "er"
    },
    {
        "card_name": "er"
    },
    {
        "card_name": "er"
    },
    {
        "card_name": "Plains",
        "number": 263,
        "shape": "normal",
        "set": "ARK",
        "position": ""
    },
    {
        "card_name": "Island",
        "number": 264,
        "shape": "normal",
        "set": "ARK",
        "position": ""
    },
    {
        "card_name": "Swamp",
        "number": 267,
        "shape": "normal",
        "set": "ARK",
        "position": ""
    },
    {
        "card_name": "Mountain",
        "number": 269,
        "shape": "normal",
        "set": "ARK",
        "position": ""
    },
    {
        "card_name": "Forest",
        "number": 270,
        "shape": "normal",
        "set": "ARK",
        "position": ""
    },
    {
        "card_name": "Plains",
        "number": 262,
        "shape": "normal",
        "set": "ARK",
        "position": ""
    },
    {
        "card_name": "Island",
        "number": 265,
        "shape": "normal",
        "set": "ARK",
        "position": ""
    },
    {
        "card_name": "Swamp",
        "number": 266,
        "shape": "normal",
        "set": "ARK",
        "position": ""
    },
    {
        "card_name": "Mountain",
        "number": 268,
        "shape": "normal",
        "set": "ARK",
        "position": ""
    },
    {
        "card_name": "Forest",
        "number": 271,
        "shape": "normal",
        "set": "ARK",
        "position": ""
    },
    {
        "card_name": "er"
    },
    {
        "card_name": "er"
    },
    {
        "card_name": "er"
    },
    {
        "card_name": "er"
    },
    "a->token",
    {
        "card_name": "Human Cleric",
        "number": 1,
        "shape": "token",
        "set": "ARK",
        "position": ""
    },
    {
        "card_name": "Human Cleric",
        "number": 2,
        "shape": "token",
        "set": "ARK",
        "position": ""
    },
    {
        "card_name": "Human Peasant",
        "number": 3,
        "shape": "token",
        "set": "ARK",
        "position": ""
    },
    {
        "card_name": "Performer",
        "number": 4,
        "shape": "token",
        "set": "ARK",
        "position": ""
    },
    {
        "card_name": "Horror",
        "number": 5,
        "shape": "token",
        "set": "ARK",
        "position": ""
    },
    {
        "card_name": "Human Wizard",
        "number": 6,
        "shape": "token",
        "set": "ARK",
        "position": ""
    },
    {
        "card_name": "Mutant",
        "number": 7,
        "shape": "token",
        "set": "ARK",
        "position": ""
    },
    {
        "card_name": "Preach",
        "number": 8,
        "shape": "token",
        "set": "ARK",
        "position": ""
    },
    {
        "card_name": "ARK Draft Archetypes",
        "number": 9,
        "shape": "token",
        "set": "ARK",
        "position": ""
    },
    {
        "card_name": "e"
    },
    {
        "card_name": "er"
    },
    {
        "card_name": "er"
    },
    {
        "card_name": "er"
    },
    {
        "card_name": "er"
    },
    {
        "card_name": "er"
    }
]