{"card_name": "Claws of Efrava", "color": "WG", "rarity": "uncommon", "type": "Creature \u2013 Cat Warrior", "number": 166, "color_identity": "WG", "cost": "{2}{G}{W}", "rules_text": "Vigilance\n{T}, Remove two counters from among creatures you control: Return Claws of Efrava to its owner's hand.", "flavor_text": "[i]Honed by generations of life in the Jamuraan oases, the Efravans were perfect hit-and-run warriors.[/i]", "pt": "4/3", "special_text": "", "shape": "normal", "set": "OVR", "loyalty": "", "artist": "Aldo Dom\u00ednguez", "notes": "", "image_type": "png"}