{"card_name": "Vestigial Snapper", "color": "UB", "rarity": "common", "type": "Creature \u2013 Phyrexian Gremlin", "number": 209, "color_identity": "UB", "cost": "{1{U}B}", "rules_text": "Vestigial Snapper can't be blocked except by Phyrexians.", "flavor_text": "[i]The ineffable variety of Phyrexia's evolutionary chain was beyond most of the coalition's understanding.[/i]", "pt": "2/1", "special_text": "", "shape": "normal", "set": "OVR", "loyalty": "", "artist": "Marin Mohan", "notes": "", "image_type": "png"}