{"card_name": "Enemy Without", "color": "R", "rarity": "rare", "type": "Sorcery", "number": 228, "color_identity": "WRG", "cost": "{2}{R}", "rules_text": "Enemy Without deals damage to target creature equal to the number of lands you control.", "flavor_text": "[i]\u201cThe Father of Machines is lord of stone and steel, sand and skin.\u201d\n\u2014[/i]Phyrexian Scriptures[i][/i]", "pt": "", "special_text": "", "shape": "fuse split", "set": "OVR", "loyalty": "", "artist": "Matt Cavotta", "card_name2": "World Within", "color2": "WG", "type2": "Sorcery", "cost2": "{4}{G}{W}", "rules_text2": "For each land you control, create a 1/1 white Soldier creature token.", "flavor_text2": "[i]\u201cThe land was your first lover, and I shall hold you until she does.\u201d\n\u2014\u201cLove Song of Night and Day\u201d[/i]", "pt2": "", "special_text2": "", "loyalty2": "", "artist2": "", "notes": "", "image_type": "png"}