{"card_name": "Grafted Canopy", "color": "", "rarity": "rare", "type": "Land \u2013 Swamp Forest", "number": 252, "color_identity": "BG", "cost": "", "rules_text": "[i]({T}: Add {B} or {G}.)[/i]\nGrafted Canopy enters the battlefield tapped unless you control a basic Mountain.", "flavor_text": "[i]Skyshroud's hardy elves adapted readily to the Rathi overly, eager to fight the Evincar on a new world.[/i]", "pt": "", "special_text": "", "shape": "normal", "set": "OVR", "loyalty": "", "artist": "Calder Moore", "notes": "", "image_type": "png"}