{"card_name": "Crushing Pressure", "color": "WU", "rarity": "rare", "type": "Sorcery", "number": 206, "color_identity": "WU", "cost": "{3}{W}{U}", "rules_text": "Tidal {W}{U} [i](As you cast this, you may pay {W}{U} and discard a card. If you do, copy it. You may choose new modes and targets for the copy.)[/i]\nChoose one \u2013\n\u2022 Destroy all creatures.\n\u2022 Return all artifacts and enchantments to their owners\u2019 hands.", "pt": "", "special_text": "", "shape": "normal", "set": "TYT", "loyalty": "", "notes": "", "image_type": "png"}