{"card_name": "Deep-Sea Gigantism", "color": "RG", "rarity": "mythic", "type": "Enchantment", "number": 208, "color_identity": "RG", "cost": "{4}{R}{G}", "rules_text": "Whenever you cast a creature spell with power 4 or greater, choose one \u2013\n\u2022 Copy that spell. [i](The copy enters as a token.)[/i]\n\u2022 Deep-Sea Gigantism deals damage to target opponent equal to that creature\u2019s power.", "pt": "", "special_text": "", "shape": "normal", "set": "TYT", "loyalty": "", "notes": "", "image_type": "png"}