{"card_name": "Sturdy Glyptodon", "color": "W", "rarity": "mythic", "type": "Creature \u2013 Beast", "number": 52, "color_identity": "W", "cost": "{1}{W}{W}", "rules_text": "Indestructible\nTrophy {3}{W}{W} [i](You may cast this from your graveyard for its trophy cost as an Aura enchantment spell with enchant Human. Exile it if it would leave the battlefield.)[/i]\nEnchanted creature has indestructible", "pt": "3/3", "special_text": "", "shape": "normal", "set": "SSF", "loyalty": "", "notes": ""}