{"card_name": "Ascended Acolyte", "color": "B", "rarity": "rare", "type": "Creature \u2013 Human Mystic", "number": 86, "color_identity": "B", "cost": "{3}{B}{B}", "rules_text": "Flying\nWhen Ascended Acolyte enters the battlefield, create two 1/1 white Eye creature tokens.\n{3}{B}, Sacrifice an Eye: Create two 1/1 white Eye creature tokens.\nSacrifice an Eye: Ascended Acolyte gains indestructible until end of turn. ", "pt": "3/3", "special_text": "", "shape": "normal", "set": "KSH", "loyalty": "", "notes": ""}